PictureTextCreator/PTC.py
PictureTextCreator/__init__.py
PictureTextCreator-0.3.0.dist-info/METADATA
PictureTextCreator-0.3.0.dist-info/WHEEL
PictureTextCreator-0.3.0.dist-info/top_level.txt
PictureTextCreator-0.3.0.dist-info/RECORD
