Metadata-Version: 2.1
Name: PictureTextCreator
Version: 0.3.0
Requires-Dist: pillow
